{
  "version": 3,
  "cmakeMinimumRequired": { "major": 3, "minor": 24, "patch": 0 },
  "configurePresets": [
    {
      "name": "release",
      "displayName": "Release (Ninja)",
      "generator": "Ninja",
      "binaryDir": "${sourceDir}/build",
      "cacheVariables": { "CMAKE_BUILD_TYPE": "Release" }
    },
    {
      "name": "debug",
      "inherits": "release",
      "displayName": "Debug (Ninja)",
      "cacheVariables": { "CMAKE_BUILD_TYPE": "Debug" }
    },
    {
      "name": "msvc",
      "displayName": "Release (Visual Studio, multi-config)",
      "generator": "Visual Studio 17 2022",
      "architecture": "x64",
      "binaryDir": "${sourceDir}/build"
    }
  ],
  "buildPresets": [
    { "name": "release", "configurePreset": "release" },
    { "name": "debug", "configurePreset": "debug" },
    { "name": "msvc", "configurePreset": "msvc", "configuration": "Release" }
  ]
}
